poke_env/__init__.py
poke_env/concurrency.py
poke_env/exceptions.py
poke_env/py.typed
poke_env/stats.py
poke_env/data/__init__.py
poke_env/data/gen_data.py
poke_env/data/normalize.py
poke_env/data/replay_template.py
poke_env/data/static/learnset.json
poke_env/data/static/natures.json
poke_env/data/static/replay_template.html
poke_env/data/static/moves/gen1moves.json
poke_env/data/static/moves/gen2moves.json
poke_env/data/static/moves/gen3moves.json
poke_env/data/static/moves/gen4moves.json
poke_env/data/static/moves/gen5moves.json
poke_env/data/static/moves/gen6moves.json
poke_env/data/static/moves/gen7moves.json
poke_env/data/static/moves/gen8moves.json
poke_env/data/static/moves/gen9moves.json
poke_env/data/static/pokedex/gen1pokedex.json
poke_env/data/static/pokedex/gen2pokedex.json
poke_env/data/static/pokedex/gen3pokedex.json
poke_env/data/static/pokedex/gen4pokedex.json
poke_env/data/static/pokedex/gen5pokedex.json
poke_env/data/static/pokedex/gen6pokedex.json
poke_env/data/static/pokedex/gen7pokedex.json
poke_env/data/static/pokedex/gen8pokedex.json
poke_env/data/static/pokedex/gen9pokedex.json
poke_env/data/static/typechart/gen1typechart.json
poke_env/data/static/typechart/gen2typechart.json
poke_env/data/static/typechart/gen3typechart.json
poke_env/data/static/typechart/gen4typechart.json
poke_env/data/static/typechart/gen5typechart.json
poke_env/data/static/typechart/gen6typechart.json
poke_env/data/static/typechart/gen7typechart.json
poke_env/data/static/typechart/gen8typechart.json
poke_env/data/static/typechart/gen9typechart.json
poke_env/environment/__init__.py
poke_env/environment/abstract_battle.py
poke_env/environment/battle.py
poke_env/environment/double_battle.py
poke_env/environment/effect.py
poke_env/environment/field.py
poke_env/environment/move.py
poke_env/environment/move_category.py
poke_env/environment/observation.py
poke_env/environment/observed_pokemon.py
poke_env/environment/pokemon.py
poke_env/environment/pokemon_gender.py
poke_env-0.8.4.dist-info/licenses/LICENSE
poke_env-0.8.4.dist-info/METADATA
poke_env-0.8.4.dist-info/WHEEL
poke_env-0.8.4.dist-info/top_level.txt
poke_env-0.8.4.dist-info/RECORD
