Metadata-Version: 2.4
Name: poke_env
Version: 0.8.4
Summary: A python interface for training Reinforcement Learning bots to battle on pokemon showdown.
Author-email: Haris Sahovic <contact@sahovic.fr>
License: MIT License
Project-URL: Documentation, https://poke-env.readthedocs.io/en/stable/
Project-URL: Repository, https://github.com/hsahovic/poke-env
Classifier: Development Status :: 3 - Alpha
Classifier: Intended Audience :: Developers
Classifier: Intended Audience :: Information Technology
Classifier: Intended Audience :: Science/Research
Classifier: License :: OSI Approved :: MIT License
Classifier: Programming Language :: Python
Classifier: Programming Language :: Python :: 3.9
Classifier: Programming Language :: Python :: 3.10
Classifier: Programming Language :: Python :: 3.11
Classifier: Programming Language :: Python :: 3.12
Classifier: Programming Language :: Python :: 3.13
Classifier: Programming Language :: Python :: 3 :: Only
Classifier: Topic :: Games/Entertainment :: Simulation
Classifier: Topic :: Games/Entertainment :: Turn Based Strategy
Classifier: Topic :: Internet
Classifier: Topic :: Scientific/Engineering :: Artificial Intelligence
Classifier: Programming Language :: Python :: Implementation :: CPython
Classifier: Programming Language :: Python :: Implementation :: PyPy
Requires-Python: >=3.9.0
License-File: LICENSE
Requires-Dist: gymnasium>=1.0.0
Requires-Dist: numpy>=2.0.2
Requires-Dist: orjson>=3.10.15
Requires-Dist: pettingzoo>=1.24.3
Requires-Dist: requests>=2.32.3
Requires-Dist: tabulate>=0.9.0
Requires-Dist: websockets==15.0.1
Provides-Extra: dev
Requires-Dist: black==25.1.0; extra == "dev"
Requires-Dist: flake8>=7.1.1; extra == "dev"
Requires-Dist: isort==6.0.1; extra == "dev"
Requires-Dist: mypy>=1.15.0; extra == "dev"
Requires-Dist: nbsphinx>=0.9.6; extra == "dev"
Requires-Dist: pre-commit>=4.1.0; extra == "dev"
Requires-Dist: pytest>=8.3.4; extra == "dev"
Requires-Dist: pytest-asyncio>=0.25.3; extra == "dev"
Requires-Dist: pytest-cov>=6.0.0; extra == "dev"
Requires-Dist: pytest-timeout>=2.3.1; extra == "dev"
Requires-Dist: sphinx>=7.4.7; extra == "dev"
Requires-Dist: sphinx-rtd-theme>=3.0.2; extra == "dev"
Requires-Dist: twine>=6.1.0; extra == "dev"
Requires-Dist: types-requests>=2.32.0.20241016; extra == "dev"
Requires-Dist: wheel>=0.45.1; extra == "dev"
Dynamic: license-file
